{
    "total_issues": 15,
    "total_original_estimate_hours": 1584.0,
    "total_time_spent_hours": 1481.5,
    "projects_count": 1,
    "projects": [
        "NBSSPORTAL"
    ],
    "avg_estimate_per_issue": 105.6,
    "avg_time_spent_per_issue": 98.76666666666667,
    "overall_efficiency": 0.9352904040404041,
    "no_transitions_tasks_count": 2,
    "open_tasks_count": 2,
    "open_tasks_time_spent_hours": 33.0,
    "completed_tasks_no_comments_count": 5,
    "clm_issues_count": 694,
    "est_issues_count": 324,
    "improvement_issues_count": 132,
    "linked_issues_count": 162,
    "filtered_issues_count": 15,
    "components_mapping": {
        "PSC": [
            "PSCPSC"
        ],
        "DMS_INV": [
            "DMS"
        ],
        "CAM+CPM+CIA": [
            "CPM"
        ],
        "NLM": [
            "NLM"
        ],
        "NWM_OCS": [
            "NWMCCS"
        ],
        "LCCM+LIS": [
            "LIS"
        ],
        "UDB_INV": [
            "UDB"
        ],
        "MNP_INV": [
            "UMNP"
        ],
        "NBSS_TEST": [
            "NBSSPORTAL"
        ],
        "GUS_INV": [
            "GUS"
        ],
        "PASS": [
            "PASS"
        ],
        "APC_CSM": [
            "CSM",
            "APC"
        ],
        "SSO+NGINX": [
            "SSO"
        ],
        "UNIGUI": [
            "UNIBLP"
        ]
    }
}